upt_nix/__init__.py
upt_nix/upt_nix.py
upt_nix/templates/base.nix
upt_nix/templates/perl.nix
upt_nix/templates/python.nix
upt_nix/tests/__init__.py
upt_nix/tests/test_nix_backend.py
upt_nix/tests/test_nix_package.py
upt_nix/tests/test_perl_package.py
upt_nix/tests/test_python_package.py
upt_nix-0.2.dist-info/LICENSE
upt_nix-0.2.dist-info/METADATA
upt_nix-0.2.dist-info/WHEEL
upt_nix-0.2.dist-info/entry_points.txt
upt_nix-0.2.dist-info/top_level.txt
upt_nix-0.2.dist-info/RECORD
