Metadata-Version: 2.1
Name: upt-nix
Version: 0.2
Summary: Nix backend for upt
Home-page: https://framagit.org/upt/upt-nix
Author: Cyril Roelandt
Author-email: tipecaml@gmail.com
License: UNKNOWN
Platform: UNKNOWN
Classifier: Development Status :: 3 - Alpha
Classifier: Intended Audience :: Developers
Classifier: License :: OSI Approved :: BSD License
Classifier: Programming Language :: Python :: 3
Classifier: Programming Language :: Python :: 3.6
Classifier: Programming Language :: Python :: 3 :: Only
Requires-Dist: jinja2
Requires-Dist: upt (>=0.6)
